data_project/__init__.py
data_project/topsisfinal.py
tanayagarwal-5.0.0.dist-info/LICENSE.txt
tanayagarwal-5.0.0.dist-info/METADATA
tanayagarwal-5.0.0.dist-info/WHEEL
tanayagarwal-5.0.0.dist-info/entry_points.txt
tanayagarwal-5.0.0.dist-info/top_level.txt
tanayagarwal-5.0.0.dist-info/RECORD
