Metadata-Version: 2.1
Name: tanayagarwal
Version: 5.0.0
Summary: topsis approach for mcdm
Home-page: 
Author: Tanay Agarwal
Author-email: tanaygupta1234@gmail.com
License: UNKNOWN
Platform: UNKNOWN
Classifier: Programming Language :: Python :: 3
Classifier: License :: OSI Approved :: MIT License
Classifier: Operating System :: OS Independent
Requires-Python: >=3.5
Requires-Dist: requests
